data_reader.py
file_search.py
gbt_rfi_gui.py
gbt_rfi_gui-1.0.13.dist-info/LICENSE.txt
gbt_rfi_gui-1.0.13.dist-info/METADATA
gbt_rfi_gui-1.0.13.dist-info/WHEEL
gbt_rfi_gui-1.0.13.dist-info/entry_points.txt
gbt_rfi_gui-1.0.13.dist-info/top_level.txt
gbt_rfi_gui-1.0.13.dist-info/RECORD
